[
  {
    "author": "Ajabreaking",
    "id": "https://nitter.net/AJABreaking/status/2046289372962599128#m",
    "url": "https://nitter.net/AJABreaking/status/2046289372962599128#m",
    "title": "عاجل | أكسيوس عن مسؤول في إدارة ترمب: من المرجح الإفراج عن الأموال الإيرانية المجمدة مقابل اتفاق مناسب",
    "content": "عاجل | أكسيوس عن مسؤول في إدارة ترمب: من المرجح الإفراج عن الأموال الإيرانية المجمدة مقابل اتفاق مناسب",
    "pubDate": "Mon, 20 Apr 2026 18:06:19 GMT"
  },
  {
    "author": "Ajabreaking",
    "id": "https://nitter.net/AJABreaking/status/2046289247187963968#m",
    "url": "https://nitter.net/AJABreaking/status/2046289247187963968#m",
    "title": "عاجل | أكسيوس عن مسؤول في إدارة ترمب: المفاوضات تراوحت بين عدم صنع سلاح نووي وعدم التخصيب داخل #إيران وتجميده مؤقتا",
    "content": "عاجل | أكسيوس عن مسؤول في إدارة ترمب: المفاوضات تراوحت بين عدم صنع سلاح نووي وعدم التخصيب داخل #إيران وتجميده مؤقتا",
    "pubDate": "Mon, 20 Apr 2026 18:05:49 GMT"
  },
  {
    "author": "Ajabreaking",
    "id": "https://nitter.net/AJABreaking/status/2046288495564480892#m",
    "url": "https://nitter.net/AJABreaking/status/2046288495564480892#m",
    "title": "عاجل | أكسيوس عن مسؤول رفيع في إدارة ترمب: لا نعرف من المسؤول في #إيران ولا هم يعرفون وهذا الأمر يجب حسمه",
    "content": "عاجل | أكسيوس عن مسؤول رفيع في إدارة ترمب: لا نعرف من المسؤول في #إيران ولا هم يعرفون وهذا الأمر يجب حسمه",
    "pubDate": "Mon, 20 Apr 2026 18:02:50 GMT"
  },
  {
    "author": "Ajabreaking",
    "id": "https://nitter.net/AJABreaking/status/2046286982532272563#m",
    "url": "https://nitter.net/AJABreaking/status/2046286982532272563#m",
    "title": "عاجل | المتحدث باسم الخارجية الأمريكية: الولايات المتحدة تستضيف جولة ثانية من التفاوض بين سفيري #لبنان وإسرائيل الخميس",
    "content": "عاجل | المتحدث باسم الخارجية الأمريكية: الولايات المتحدة تستضيف جولة ثانية من التفاوض بين سفيري #لبنان وإسرائيل الخميس",
    "pubDate": "Mon, 20 Apr 2026 17:56:49 GMT"
  },
  {
    "author": "Ajabreaking",
    "id": "https://nitter.net/AJABreaking/status/2046286606147948863#m",
    "url": "https://nitter.net/AJABreaking/status/2046286606147948863#m",
    "title": "عاجل | ترمب: لست تحت ضغط من أي نوع لإبرام اتفاق مع #إيران لكن ذلك سيحدث وسريعا نسبيا",
    "content": "عاجل | ترمب: لست تحت ضغط من أي نوع لإبرام اتفاق مع #إيران لكن ذلك سيحدث وسريعا نسبيا",
    "pubDate": "Mon, 20 Apr 2026 17:55:19 GMT"
  },
  {
    "author": "Ajabreaking",
    "id": "https://nitter.net/AJABreaking/status/2046285849092915577#m",
    "url": "https://nitter.net/AJABreaking/status/2046285849092915577#m",
    "title": "عاجل | ترمب: العملية في #إيران تنفذ بإتقان تام على غرار ما حدث في فنزويلا غير أنها أضخم وأكثر تعقيدا",
    "content": "عاجل | ترمب: العملية في #إيران تنفذ بإتقان تام على غرار ما حدث في فنزويلا غير أنها أضخم وأكثر تعقيدا",
    "pubDate": "Mon, 20 Apr 2026 17:52:19 GMT"
  },
  {
    "author": "Ajabreaking",
    "id": "https://nitter.net/AJABreaking/status/2046285597526925420#m",
    "url": "https://nitter.net/AJABreaking/status/2046285597526925420#m",
    "title": "عاجل | ترمب: بدأنا هذه المهمة بشأن #إيران وسننجزها على الوجه الصحيح",
    "content": "عاجل | ترمب: بدأنا هذه المهمة بشأن #إيران وسننجزها على الوجه الصحيح",
    "pubDate": "Mon, 20 Apr 2026 17:51:19 GMT"
  },
  {
    "author": "Ajabreaking",
    "id": "https://nitter.net/AJABreaking/status/2046285473740423598#m",
    "url": "https://nitter.net/AJABreaking/status/2046285473740423598#m",
    "title": "عاجل | وزارة الصحة اللبنانية: 6 مصابين إثر غارة إسرائيلية على بلدة قعقعية الجسر جنوبي البلاد",
    "content": "عاجل | وزارة الصحة اللبنانية: 6 مصابين إثر غارة إسرائيلية على بلدة قعقعية الجسر جنوبي البلاد",
    "pubDate": "Mon, 20 Apr 2026 17:50:49 GMT"
  },
  {
    "author": "Ajabreaking",
    "id": "https://nitter.net/AJABreaking/status/2046285095728812302#m",
    "url": "https://nitter.net/AJABreaking/status/2046285095728812302#m",
    "title": "عاجل | ترمب: لن أسمح للديمقراطيين الخونة بالتقليل من شأن الإنجازات التي حققتها قواتنا وإدارتي في #إيران",
    "content": "عاجل | ترمب: لن أسمح للديمقراطيين الخونة بالتقليل من شأن الإنجازات التي حققتها قواتنا وإدارتي في #إيران",
    "pubDate": "Mon, 20 Apr 2026 17:49:19 GMT"
  },
  {
    "author": "Ajabreaking",
    "id": "https://nitter.net/AJABreaking/status/2046284967882244512#m",
    "url": "https://nitter.net/AJABreaking/status/2046284967882244512#m",
    "title": "عاجل | ترمب: لن أسمح للديمقراطيين بدفع أمريكا للتعجل في إبرام اتفاق مع #إيران لا يرقى إلى المستوى الأمثل",
    "content": "عاجل | ترمب: لن أسمح للديمقراطيين بدفع أمريكا للتعجل في إبرام اتفاق مع #إيران لا يرقى إلى المستوى الأمثل",
    "pubDate": "Mon, 20 Apr 2026 17:48:49 GMT"
  },
  {
    "author": "Ajabreaking",
    "id": "https://nitter.net/AJABreaking/status/2046284840140485117#m",
    "url": "https://nitter.net/AJABreaking/status/2046284840140485117#m",
    "title": "عاجل | ترمب: لست تحت ضغط من أي نوع لإبرام اتفاق مع #إيران",
    "content": "عاجل | ترمب: لست تحت ضغط من أي نوع لإبرام اتفاق مع #إيران",
    "pubDate": "Mon, 20 Apr 2026 17:48:18 GMT"
  },
  {
    "author": "Ajabreaking",
    "id": "https://nitter.net/AJABreaking/status/2046284748733976857#m",
    "url": "https://nitter.net/AJABreaking/status/2046284748733976857#m",
    "title": "عاجل | ترمب: الاتفاق مع #إيران سيكون إنجازا يفخر به العالم بدلا من سنوات إذلال تحملناها جراء قيادة تفتقر للكفاءة",
    "content": "عاجل | ترمب: الاتفاق مع #إيران سيكون إنجازا يفخر به العالم بدلا من سنوات إذلال تحملناها جراء قيادة تفتقر للكفاءة",
    "pubDate": "Mon, 20 Apr 2026 17:47:56 GMT"
  },
  {
    "author": "Ajabreaking",
    "id": "https://nitter.net/AJABreaking/status/2046283971122667730#m",
    "url": "https://nitter.net/AJABreaking/status/2046283971122667730#m",
    "title": "عاجل | ترمب: إذا توصلنا لاتفاق مع #إيران فسيضمن السلام والأمن لإسرائيل والشرق الأوسط وأوروبا وأمريكا وسائر العالم",
    "content": "عاجل | ترمب: إذا توصلنا لاتفاق مع #إيران فسيضمن السلام والأمن لإسرائيل والشرق الأوسط وأوروبا وأمريكا وسائر العالم",
    "pubDate": "Mon, 20 Apr 2026 17:44:51 GMT"
  },
  {
    "author": "Ajabreaking",
    "id": "https://nitter.net/AJABreaking/status/2046283854508331198#m",
    "url": "https://nitter.net/AJABreaking/status/2046283854508331198#m",
    "title": "عاجل | ترمب: لولا إنهائي للاتفاق النووي لكانت الأسلحة النووية استخدمت ضد إسرائيل وفي الشرق الأوسط بما في ذلك قواعدنا",
    "content": "عاجل | ترمب: لولا إنهائي للاتفاق النووي لكانت الأسلحة النووية استخدمت ضد إسرائيل وفي الشرق الأوسط بما في ذلك قواعدنا",
    "pubDate": "Mon, 20 Apr 2026 17:44:23 GMT"
  },
  {
    "author": "Ajabreaking",
    "id": "https://nitter.net/AJABreaking/status/2046283079661023281#m",
    "url": "https://nitter.net/AJABreaking/status/2046283079661023281#m",
    "title": "عاجل | ترمب: الاتفاق النووي السابق كان طريقا مضمونا لحصول #إيران على سلاح نووي وهذا لن يحدث في الاتفاق الذي نعمل عليه",
    "content": "عاجل | ترمب: الاتفاق النووي السابق كان طريقا مضمونا لحصول #إيران على سلاح نووي وهذا لن يحدث في الاتفاق الذي نعمل عليه",
    "pubDate": "Mon, 20 Apr 2026 17:41:18 GMT"
  },
  {
    "author": "Ajabreaking",
    "id": "https://nitter.net/AJABreaking/status/2046282576596209816#m",
    "url": "https://nitter.net/AJABreaking/status/2046282576596209816#m",
    "title": "عاجل | ترمب: الاتفاق الذي نعمل عليه مع #إيران سيكون أفضل بكثير من الاتفاق النووي الذي وقع عليه أوباما",
    "content": "عاجل | ترمب: الاتفاق الذي نعمل عليه مع #إيران سيكون أفضل بكثير من الاتفاق النووي الذي وقع عليه أوباما",
    "pubDate": "Mon, 20 Apr 2026 17:39:19 GMT"
  },
  {
    "author": "Ajabreaking",
    "id": "https://nitter.net/AJABreaking/status/2046282450448372080#m",
    "url": "https://nitter.net/AJABreaking/status/2046282450448372080#m",
    "title": "عاجل | ترمب: الاتفاق الذي نعمل عليه حاليا مع #إيران سيكون أفضل بكثير من اتفاق 2015 النووي",
    "content": "عاجل | ترمب: الاتفاق الذي نعمل عليه حاليا مع #إيران سيكون أفضل بكثير من اتفاق 2015 النووي",
    "pubDate": "Mon, 20 Apr 2026 17:38:48 GMT"
  },
  {
    "author": "Ajabreaking",
    "id": "https://nitter.net/AJABreaking/status/2046282325474889755#m",
    "url": "https://nitter.net/AJABreaking/status/2046282325474889755#m",
    "title": "عاجل | أكسيوس عن مسؤولين أمريكيين: التراجع عن فتح مضيق هرمز يدل على انقسام بين رئيس برلمان #إيران وقائد الحرس الثوري",
    "content": "عاجل | أكسيوس عن مسؤولين أمريكيين: التراجع عن فتح مضيق هرمز يدل على انقسام بين رئيس برلمان #إيران وقائد الحرس الثوري",
    "pubDate": "Mon, 20 Apr 2026 17:38:19 GMT"
  },
  {
    "author": "Ajabreaking",
    "id": "https://nitter.net/AJABreaking/status/2046281821323739202#m",
    "url": "https://nitter.net/AJABreaking/status/2046281821323739202#m",
    "title": "عاجل | أكسيوس عن مسؤول أمريكي: ترمب لا يريد القتال بعد الآن لكنه سيفعل إذا شعر أنه مضطر",
    "content": "عاجل | أكسيوس عن مسؤول أمريكي: ترمب لا يريد القتال بعد الآن لكنه سيفعل إذا شعر أنه مضطر",
    "pubDate": "Mon, 20 Apr 2026 17:36:18 GMT"
  },
  {
    "author": "Ajabreaking",
    "id": "https://nitter.net/AJABreaking/status/2046281695603597766#m",
    "url": "https://nitter.net/AJABreaking/status/2046281695603597766#m",
    "title": "عاجل | أكسيوس عن مسؤول أمريكي: ترمب سئم الأمر ويريد إنهاءه ولا يعجبه أن تسيطر #إيران على مضيق هرمز وأن تستخدمه ضدنا",
    "content": "عاجل | أكسيوس عن مسؤول أمريكي: ترمب سئم الأمر ويريد إنهاءه ولا يعجبه أن تسيطر #إيران على مضيق هرمز وأن تستخدمه ضدنا",
    "pubDate": "Mon, 20 Apr 2026 17:35:48 GMT"
  },
  {
    "author": "alarabiya_brk",
    "id": "https://nitter.net/AlArabiya_Brk/status/2046287996593303661#m",
    "url": "https://nitter.net/AlArabiya_Brk/status/2046287996593303661#m",
    "title": "ترمب: الاتفاق الجديد مع إيران سيكون أفضل من القديم #العربية_عاجل",
    "content": "ترمب: الاتفاق الجديد مع إيران سيكون أفضل من القديم #العربية_عاجل",
    "pubDate": "Mon, 20 Apr 2026 18:00:51 GMT"
  },
  {
    "author": "alarabiya_brk",
    "id": "https://nitter.net/AlArabiya_Brk/status/2046286781268492652#m",
    "url": "https://nitter.net/AlArabiya_Brk/status/2046286781268492652#m",
    "title": "ترمب: سيتم إنجاز الاتفاق مع إيران بشكل مثالي وعلى نطاق يشبه ما حدث في فنزويلا #العربية_عاجل",
    "content": "ترمب: سيتم إنجاز الاتفاق مع إيران بشكل مثالي وعلى نطاق يشبه ما حدث في فنزويلا #العربية_عاجل",
    "pubDate": "Mon, 20 Apr 2026 17:56:01 GMT"
  },
  {
    "author": "alarabiya_brk",
    "id": "https://nitter.net/AlArabiya_Brk/status/2046286291214455283#m",
    "url": "https://nitter.net/AlArabiya_Brk/status/2046286291214455283#m",
    "title": "ترمب: لن أسمح للديمقراطيين الخونة بالتقليل مما يحدث مع إيران #العربية_عاجل",
    "content": "ترمب: لن أسمح للديمقراطيين الخونة بالتقليل مما يحدث مع إيران #العربية_عاجل",
    "pubDate": "Mon, 20 Apr 2026 17:54:04 GMT"
  },
  {
    "author": "alarabiya_brk",
    "id": "https://nitter.net/AlArabiya_Brk/status/2046286078848496055#m",
    "url": "https://nitter.net/AlArabiya_Brk/status/2046286078848496055#m",
    "title": "ترمب عن الاتفاق مع إيران: كل شيء سيحدث بسرعة نسبية #العربية_عاجل",
    "content": "ترمب عن الاتفاق مع إيران: كل شيء سيحدث بسرعة نسبية #العربية_عاجل",
    "pubDate": "Mon, 20 Apr 2026 17:53:14 GMT"
  },
  {
    "author": "alarabiya_brk",
    "id": "https://nitter.net/AlArabiya_Brk/status/2046285750304399552#m",
    "url": "https://nitter.net/AlArabiya_Brk/status/2046285750304399552#m",
    "title": "ترمب: كان إنجاز العملية العسكرية في إيران أسرع بكثير مما أعلن #العربية_عاجل",
    "content": "ترمب: كان إنجاز العملية العسكرية في إيران أسرع بكثير مما أعلن #العربية_عاجل",
    "pubDate": "Mon, 20 Apr 2026 17:51:55 GMT"
  },
  {
    "author": "alarabiya_brk",
    "id": "https://nitter.net/AlArabiya_Brk/status/2046285664526713019#m",
    "url": "https://nitter.net/AlArabiya_Brk/status/2046285664526713019#m",
    "title": "ترمب: لن أسمح للديمقراطيين بالدفع نحو اتفاق سيئ مع إيران #العربية_عاجل",
    "content": "ترمب: لن أسمح للديمقراطيين بالدفع نحو اتفاق سيئ مع إيران #العربية_عاجل",
    "pubDate": "Mon, 20 Apr 2026 17:51:35 GMT"
  },
  {
    "author": "alarabiya_brk",
    "id": "https://nitter.net/AlArabiya_Brk/status/2046285004674597211#m",
    "url": "https://nitter.net/AlArabiya_Brk/status/2046285004674597211#m",
    "title": "ترمب: الديمقراطيون يقومون بكل ما يمكنهم للإضرار بموقفنا القوي للغاية تجاه إيران #العربية_عاجل",
    "content": "ترمب: الديمقراطيون يقومون بكل ما يمكنهم للإضرار بموقفنا القوي للغاية تجاه إيران #العربية_عاجل",
    "pubDate": "Mon, 20 Apr 2026 17:48:57 GMT"
  },
  {
    "author": "alarabiya_brk",
    "id": "https://nitter.net/AlArabiya_Brk/status/2046284218938834980#m",
    "url": "https://nitter.net/AlArabiya_Brk/status/2046284218938834980#m",
    "title": "ترمب: امتلاك إيران السلاح النووي كان سيمكنها من تهديد قواعدنا بالمنطقة وبأميركا #العربية_عاجل",
    "content": "ترمب: امتلاك إيران السلاح النووي كان سيمكنها من تهديد قواعدنا بالمنطقة وبأميركا #العربية_عاجل",
    "pubDate": "Mon, 20 Apr 2026 17:45:50 GMT"
  },
  {
    "author": "alarabiya_brk",
    "id": "https://nitter.net/AlArabiya_Brk/status/2046283754130309270#m",
    "url": "https://nitter.net/AlArabiya_Brk/status/2046283754130309270#m",
    "title": "ترمب: لست تحت ضغط من أي نوع لإبرام اتفاق مع إيران #العربية_عاجل",
    "content": "ترمب: لست تحت ضغط من أي نوع لإبرام اتفاق مع إيران #العربية_عاجل",
    "pubDate": "Mon, 20 Apr 2026 17:43:59 GMT"
  },
  {
    "author": "alarabiya_brk",
    "id": "https://nitter.net/AlArabiya_Brk/status/2046283539876876535#m",
    "url": "https://nitter.net/AlArabiya_Brk/status/2046283539876876535#m",
    "title": "ترمب: التوصل إلى اتفاق مع إيران سيضمن السلام والأمن للمنطقة #العربية_عاجل",
    "content": "ترمب: التوصل إلى اتفاق مع إيران سيضمن السلام والأمن للمنطقة #العربية_عاجل",
    "pubDate": "Mon, 20 Apr 2026 17:43:08 GMT"
  },
  {
    "author": "alarabiya_brk",
    "id": "https://nitter.net/AlArabiya_Brk/status/2046283458880614703#m",
    "url": "https://nitter.net/AlArabiya_Brk/status/2046283458880614703#m",
    "title": "ترمب: لو لم أنْهِ الاتفاق النووي لكانت أسلحة إيران النووية استخدمت ضد إسرائيل والمنطقة #العربية_عاجل",
    "content": "ترمب: لو لم أنْهِ الاتفاق النووي لكانت أسلحة إيران النووية استخدمت ضد إسرائيل والمنطقة #العربية_عاجل",
    "pubDate": "Mon, 20 Apr 2026 17:42:49 GMT"
  },
  {
    "author": "alarabiya_brk",
    "id": "https://nitter.net/AlArabiya_Brk/status/2046282583810453967#m",
    "url": "https://nitter.net/AlArabiya_Brk/status/2046282583810453967#m",
    "title": "ترمب: امتلاك إيران للسلاح النووي لن يحدث في ظل الاتفاق الذي نعمل عليه #العربية_عاجل",
    "content": "ترمب: امتلاك إيران للسلاح النووي لن يحدث في ظل الاتفاق الذي نعمل عليه #العربية_عاجل",
    "pubDate": "Mon, 20 Apr 2026 17:39:20 GMT"
  },
  {
    "author": "alarabiya_brk",
    "id": "https://nitter.net/AlArabiya_Brk/status/2046282414519947452#m",
    "url": "https://nitter.net/AlArabiya_Brk/status/2046282414519947452#m",
    "title": "ترمب: اتفاق أوباما مع إيران أحد أسوأ الاتفاقات التي أبرمت على الإطلاق #العربية_عاجل",
    "content": "ترمب: اتفاق أوباما مع إيران أحد أسوأ الاتفاقات التي أبرمت على الإطلاق #العربية_عاجل",
    "pubDate": "Mon, 20 Apr 2026 17:38:40 GMT"
  },
  {
    "author": "alarabiya_brk",
    "id": "https://nitter.net/AlArabiya_Brk/status/2046282212601979010#m",
    "url": "https://nitter.net/AlArabiya_Brk/status/2046282212601979010#m",
    "title": "ترمب: الصفقة مع إيران ستكون أفضل بكثير من الاتفاق النووي عام 2015 #العربية_عاجل",
    "content": "ترمب: الصفقة مع إيران ستكون أفضل بكثير من الاتفاق النووي عام 2015 #العربية_عاجل",
    "pubDate": "Mon, 20 Apr 2026 17:37:52 GMT"
  },
  {
    "author": "alarabiya_brk",
    "id": "https://nitter.net/AlArabiya_Brk/status/2046280525363442078#m",
    "url": "https://nitter.net/AlArabiya_Brk/status/2046280525363442078#m",
    "title": "هيئة البث: وفدا إسرائيل ولبنان سيناقشان مسألة الحدود البرية الخميس #العربية_عاجل",
    "content": "هيئة البث: وفدا إسرائيل ولبنان سيناقشان مسألة الحدود البرية الخميس #العربية_عاجل",
    "pubDate": "Mon, 20 Apr 2026 17:31:09 GMT"
  },
  {
    "author": "alarabiya_brk",
    "id": "https://nitter.net/AlArabiya_Brk/status/2046280155035787311#m",
    "url": "https://nitter.net/AlArabiya_Brk/status/2046280155035787311#m",
    "title": "هيئة البث: مفاوضات الخميس بين إسرائيل ولبنان ستبحث إمكانية تمديد الهدنة #العربية_عاجل",
    "content": "هيئة البث: مفاوضات الخميس بين إسرائيل ولبنان ستبحث إمكانية تمديد الهدنة #العربية_عاجل",
    "pubDate": "Mon, 20 Apr 2026 17:29:41 GMT"
  },
  {
    "author": "alarabiya_brk",
    "id": "https://nitter.net/AlArabiya_Brk/status/2046270652194157019#m",
    "url": "https://nitter.net/AlArabiya_Brk/status/2046270652194157019#m",
    "title": "مصدر باكستاني للعربية: نتوقع وصول الوفد الإيراني إلى إسلام آباد صباح الثلاثاء #العربية_عاجل",
    "content": "مصدر باكستاني للعربية: نتوقع وصول الوفد الإيراني إلى إسلام آباد صباح الثلاثاء #العربية_عاجل",
    "pubDate": "Mon, 20 Apr 2026 16:51:56 GMT"
  },
  {
    "author": "alarabiya_brk",
    "id": "https://nitter.net/AlArabiya_Brk/status/2046268246442037337#m",
    "url": "https://nitter.net/AlArabiya_Brk/status/2046268246442037337#m",
    "title": "إعلام إيراني يتراجع ويقول إن وفد طهران سيغادر إلى باكستان الثلاثاء #العربية_عاجل",
    "content": "إعلام إيراني يتراجع ويقول إن وفد طهران سيغادر إلى باكستان الثلاثاء #العربية_عاجل",
    "pubDate": "Mon, 20 Apr 2026 16:42:22 GMT"
  },
  {
    "author": "alarabiya_brk",
    "id": "https://nitter.net/AlArabiya_Brk/status/2046258799816675706#m",
    "url": "https://nitter.net/AlArabiya_Brk/status/2046258799816675706#m",
    "title": "واس: ولي العهد السعودي ورئيس مجلس السيادة السوداني أكدا أهمية الحفاظ على سيادة السودان #العربية_عاجل",
    "content": "واس: ولي العهد السعودي ورئيس مجلس السيادة السوداني أكدا أهمية الحفاظ على سيادة السودان #العربية_عاجل",
    "pubDate": "Mon, 20 Apr 2026 16:04:50 GMT"
  },
  {
    "author": "alarabiya_brk",
    "id": "https://nitter.net/AlArabiya_Brk/status/2046258561357918427#m",
    "url": "https://nitter.net/AlArabiya_Brk/status/2046258561357918427#m",
    "title": "واس: ولي العهد السعودي ورئيس مجلس السيادة السوداني يؤكدان على ضمان أمن واستقرار السودان #العربية_عاجل",
    "content": "واس: ولي العهد السعودي ورئيس مجلس السيادة السوداني يؤكدان على ضمان أمن واستقرار السودان #العربية_عاجل",
    "pubDate": "Mon, 20 Apr 2026 16:03:53 GMT"
  }
]