[
  {
    "author": "Ajabreaking",
    "id": "https://nitter.net/AJABreaking/status/2036579039993835586#m",
    "url": "https://nitter.net/AJABreaking/status/2036579039993835586#m",
    "title": "عاجل | الجيش الإسرائيلي: بدأنا شن هجمات جديدة تستهدف بنى تحتية تابعة للنظام الإيراني في #طهران",
    "content": "عاجل | الجيش الإسرائيلي: بدأنا شن هجمات جديدة تستهدف بنى تحتية تابعة للنظام الإيراني في #طهران",
    "pubDate": "Tue, 24 Mar 2026 23:00:55 GMT"
  },
  {
    "author": "Ajabreaking",
    "id": "https://nitter.net/AJABreaking/status/2036578914093445199#m",
    "url": "https://nitter.net/AJABreaking/status/2036578914093445199#m",
    "title": "عاجل | الحكومة الكندية: يجب وقف هجمات #حزب_الله على إسرائيل ونزع سلاحه",
    "content": "عاجل | الحكومة الكندية: يجب وقف هجمات #حزب_الله على إسرائيل ونزع سلاحه",
    "pubDate": "Tue, 24 Mar 2026 23:00:25 GMT"
  },
  {
    "author": "Ajabreaking",
    "id": "https://nitter.net/AJABreaking/status/2036578788469842187#m",
    "url": "https://nitter.net/AJABreaking/status/2036578788469842187#m",
    "title": "عاجل | الحكومة الكندية: لا يجوز انتهاك سيادة #لبنان ووحدة أراضيه",
    "content": "عاجل | الحكومة الكندية: لا يجوز انتهاك سيادة #لبنان ووحدة أراضيه",
    "pubDate": "Tue, 24 Mar 2026 22:59:55 GMT"
  },
  {
    "author": "Ajabreaking",
    "id": "https://nitter.net/AJABreaking/status/2036578662397456639#m",
    "url": "https://nitter.net/AJABreaking/status/2036578662397456639#m",
    "title": "عاجل | الوكالة الدولية للطاقة الذرية: إيران أكدت عدم وقوع أي أضرار في المحطة أو إصابات بين العاملين",
    "content": "عاجل | الوكالة الدولية للطاقة الذرية: إيران أكدت عدم وقوع أي أضرار في المحطة أو إصابات بين العاملين",
    "pubDate": "Tue, 24 Mar 2026 22:59:25 GMT"
  },
  {
    "author": "Ajabreaking",
    "id": "https://nitter.net/AJABreaking/status/2036578536828412181#m",
    "url": "https://nitter.net/AJABreaking/status/2036578536828412181#m",
    "title": "عاجل | الوكالة الدولية للطاقة الذرية: إيران أبلغتنا بسقوط قذيفة أخرى بمحيط محطة بوشهر النووية",
    "content": "عاجل | الوكالة الدولية للطاقة الذرية: إيران أبلغتنا بسقوط قذيفة أخرى بمحيط محطة بوشهر النووية",
    "pubDate": "Tue, 24 Mar 2026 22:58:55 GMT"
  },
  {
    "author": "Ajabreaking",
    "id": "https://nitter.net/AJABreaking/status/2036578159135433081#m",
    "url": "https://nitter.net/AJABreaking/status/2036578159135433081#m",
    "title": "عاجل | الجبهة الداخلية الإسرائيلية: رصد إطلاق صواريخ من #إيران نحو إيلات ومحيطها جنوب إسرائيل",
    "content": "عاجل | الجبهة الداخلية الإسرائيلية: رصد إطلاق صواريخ من #إيران نحو إيلات ومحيطها جنوب إسرائيل",
    "pubDate": "Tue, 24 Mar 2026 22:57:25 GMT"
  },
  {
    "author": "Ajabreaking",
    "id": "https://nitter.net/AJABreaking/status/2036577781820088538#m",
    "url": "https://nitter.net/AJABreaking/status/2036577781820088538#m",
    "title": "عاجل | الحكومة الكندية: نندد بشدة بخطط إسرائيل لاحتلال أراض في جنوب #لبنان",
    "content": "عاجل | الحكومة الكندية: نندد بشدة بخطط إسرائيل لاحتلال أراض في جنوب #لبنان",
    "pubDate": "Tue, 24 Mar 2026 22:55:55 GMT"
  },
  {
    "author": "Ajabreaking",
    "id": "https://nitter.net/AJABreaking/status/2036576653661389004#m",
    "url": "https://nitter.net/AJABreaking/status/2036576653661389004#m",
    "title": "عاجل | مراسل #الجزيرة: دوي انفجارات في غرب العاصمة الإيرانية #طهران",
    "content": "عاجل | مراسل #الجزيرة: دوي انفجارات في غرب العاصمة الإيرانية #طهران",
    "pubDate": "Tue, 24 Mar 2026 22:51:26 GMT"
  },
  {
    "author": "Ajabreaking",
    "id": "https://nitter.net/AJABreaking/status/2036576146146340885#m",
    "url": "https://nitter.net/AJABreaking/status/2036576146146340885#m",
    "title": "عاجل | القناة 12 الإسرائيلية: اعتراض الصاروخ الذي أطلق من #إيران نحو إيلات وهو الثاني خلال الساعة الأخيرة",
    "content": "عاجل | القناة 12 الإسرائيلية: اعتراض الصاروخ الذي أطلق من #إيران نحو إيلات وهو الثاني خلال الساعة الأخيرة",
    "pubDate": "Tue, 24 Mar 2026 22:49:25 GMT"
  },
  {
    "author": "Ajabreaking",
    "id": "https://nitter.net/AJABreaking/status/2036575264629465442#m",
    "url": "https://nitter.net/AJABreaking/status/2036575264629465442#m",
    "title": "عاجل | مراسل #الجزيرة: غارة إسرائيلية على بلدة الشرقية في قضاء النبطية جنوبي #لبنان",
    "content": "عاجل | مراسل #الجزيرة: غارة إسرائيلية على بلدة الشرقية في قضاء النبطية جنوبي #لبنان",
    "pubDate": "Tue, 24 Mar 2026 22:45:55 GMT"
  },
  {
    "author": "Ajabreaking",
    "id": "https://nitter.net/AJABreaking/status/2036574761271038358#m",
    "url": "https://nitter.net/AJABreaking/status/2036574761271038358#m",
    "title": "عاجل | الجبهة الداخلية الإسرائيلية: إطلاق صفارات الإنذار في مدينة إيلات ومحيطها جنوب إسرائيل",
    "content": "عاجل | الجبهة الداخلية الإسرائيلية: إطلاق صفارات الإنذار في مدينة إيلات ومحيطها جنوب إسرائيل",
    "pubDate": "Tue, 24 Mar 2026 22:43:55 GMT"
  },
  {
    "author": "Ajabreaking",
    "id": "https://nitter.net/AJABreaking/status/2036572877399417256#m",
    "url": "https://nitter.net/AJABreaking/status/2036572877399417256#m",
    "title": "عاجل | وزارة الصحة اللبنانية: 4 شهداء ومصاب جراء غارة إسرائيلية على بلدة عدلون جنوبي البلاد",
    "content": "عاجل | وزارة الصحة اللبنانية: 4 شهداء ومصاب جراء غارة إسرائيلية على بلدة عدلون جنوبي البلاد",
    "pubDate": "Tue, 24 Mar 2026 22:36:26 GMT"
  },
  {
    "author": "Ajabreaking",
    "id": "https://nitter.net/AJABreaking/status/2036572496724398347#m",
    "url": "https://nitter.net/AJABreaking/status/2036572496724398347#m",
    "title": "عاجل | وزارة الدفاع البريطانية: مناطق القواعد ذات السيادة لم تكن جزءا من جمهورية قبرص وليس لدينا أي خطط لتغيير ذلك",
    "content": "عاجل | وزارة الدفاع البريطانية: مناطق القواعد ذات السيادة لم تكن جزءا من جمهورية قبرص وليس لدينا أي خطط لتغيير ذلك",
    "pubDate": "Tue, 24 Mar 2026 22:34:55 GMT"
  },
  {
    "author": "Ajabreaking",
    "id": "https://nitter.net/AJABreaking/status/2036572244311200180#m",
    "url": "https://nitter.net/AJABreaking/status/2036572244311200180#m",
    "title": "عاجل | رئيس شركة شل: أوروبا معرضة لخطر نقص الوقود ابتداء من الشهر المقبل",
    "content": "عاجل | رئيس شركة شل: أوروبا معرضة لخطر نقص الوقود ابتداء من الشهر المقبل",
    "pubDate": "Tue, 24 Mar 2026 22:33:55 GMT"
  },
  {
    "author": "Ajabreaking",
    "id": "https://nitter.net/AJABreaking/status/2036572118507233690#m",
    "url": "https://nitter.net/AJABreaking/status/2036572118507233690#m",
    "title": "عاجل | مراسل #الجزيرة: غارتان إسرائيليتان على بلدتي فرون وباتوليه في جنوب #لبنان",
    "content": "عاجل | مراسل #الجزيرة: غارتان إسرائيليتان على بلدتي فرون وباتوليه في جنوب #لبنان",
    "pubDate": "Tue, 24 Mar 2026 22:33:25 GMT"
  },
  {
    "author": "Ajabreaking",
    "id": "https://nitter.net/AJABreaking/status/2036571992703271000#m",
    "url": "https://nitter.net/AJABreaking/status/2036571992703271000#m",
    "title": "عاجل | وزارة الصحة اللبنانية: شهيدان و4 مصابين جراء الغارة الإسرائيلية على منطقة المية ومية جنوبي #لبنان",
    "content": "عاجل | وزارة الصحة اللبنانية: شهيدان و4 مصابين جراء الغارة الإسرائيلية على منطقة المية ومية جنوبي #لبنان",
    "pubDate": "Tue, 24 Mar 2026 22:32:55 GMT"
  },
  {
    "author": "Ajabreaking",
    "id": "https://nitter.net/AJABreaking/status/2036571237640540425#m",
    "url": "https://nitter.net/AJABreaking/status/2036571237640540425#m",
    "title": "عاجل | سي إن إن عن مصادر: إيران أبلغت وشنطن أنها لا ترغب في استئناف المفاوضات مع ويتكوف وكوشنر وتفضل نائب الرئيس",
    "content": "عاجل | سي إن إن عن مصادر: إيران أبلغت وشنطن أنها لا ترغب في استئناف المفاوضات مع ويتكوف وكوشنر وتفضل نائب الرئيس",
    "pubDate": "Tue, 24 Mar 2026 22:29:55 GMT"
  },
  {
    "author": "Ajabreaking",
    "id": "https://nitter.net/AJABreaking/status/2036569855516664255#m",
    "url": "https://nitter.net/AJABreaking/status/2036569855516664255#m",
    "title": "عاجل | التلغراف عن مصادر: قبرص تطالب باتفاق أمني جديد بشأن القواعد البريطانية بعد هجوم إيراني على منشآت بريطانية",
    "content": "عاجل | التلغراف عن مصادر: قبرص تطالب باتفاق أمني جديد بشأن القواعد البريطانية بعد هجوم إيراني على منشآت بريطانية",
    "pubDate": "Tue, 24 Mar 2026 22:24:25 GMT"
  },
  {
    "author": "Ajabreaking",
    "id": "https://nitter.net/AJABreaking/status/2036567974941782435#m",
    "url": "https://nitter.net/AJABreaking/status/2036567974941782435#m",
    "title": "عاجل | وكالة إيسنا: اتصال بين الرئيسين الإيراني والفرنسي بحثا خلاله العدوان على #إيران وموضوع الملاحة في مضيق هرمز",
    "content": "عاجل | وكالة إيسنا: اتصال بين الرئيسين الإيراني والفرنسي بحثا خلاله العدوان على #إيران وموضوع الملاحة في مضيق هرمز",
    "pubDate": "Tue, 24 Mar 2026 22:16:57 GMT"
  },
  {
    "author": "Ajabreaking",
    "id": "https://nitter.net/AJABreaking/status/2036567591288778802#m",
    "url": "https://nitter.net/AJABreaking/status/2036567591288778802#m",
    "title": "عاجل | البعثة الإيرانية لدى الأمم المتحدة: السفن غير المعادية بإمكانها عبور مضيق هرمز بالتنسيق مع السلطات الإيرانية",
    "content": "عاجل | البعثة الإيرانية لدى الأمم المتحدة: السفن غير المعادية بإمكانها عبور مضيق هرمز بالتنسيق مع السلطات الإيرانية",
    "pubDate": "Tue, 24 Mar 2026 22:15:26 GMT"
  },
  {
    "author": "alarabiya_brk",
    "id": "https://nitter.net/AlArabiya_Brk/status/2036579418278154624#m",
    "url": "https://nitter.net/AlArabiya_Brk/status/2036579418278154624#m",
    "title": "الكويت: أضرار مادية فقط جراء حريق في خزان وقود بمطار الكويت #العربية_عاجل",
    "content": "الكويت: أضرار مادية فقط جراء حريق في خزان وقود بمطار الكويت #العربية_عاجل",
    "pubDate": "Tue, 24 Mar 2026 23:02:25 GMT"
  },
  {
    "author": "alarabiya_brk",
    "id": "https://nitter.net/AlArabiya_Brk/status/2036579247758750013#m",
    "url": "https://nitter.net/AlArabiya_Brk/status/2036579247758750013#m",
    "title": "الكويت: التعامل مع حريق جراء استهداف مسيرات لخزان وقود بمطار الكويت  #العربية_عاجل",
    "content": "الكويت: التعامل مع حريق جراء استهداف مسيرات لخزان وقود بمطار الكويت  #العربية_عاجل",
    "pubDate": "Tue, 24 Mar 2026 23:01:45 GMT"
  },
  {
    "author": "alarabiya_brk",
    "id": "https://nitter.net/AlArabiya_Brk/status/2036578650028429528#m",
    "url": "https://nitter.net/AlArabiya_Brk/status/2036578650028429528#m",
    "title": "الجيش الإسرائيلي: بدأنا هجمات على طهران #العربية_عاجل",
    "content": "الجيش الإسرائيلي: بدأنا هجمات على طهران #العربية_عاجل",
    "pubDate": "Tue, 24 Mar 2026 22:59:22 GMT"
  },
  {
    "author": "alarabiya_brk",
    "id": "https://nitter.net/AlArabiya_Brk/status/2036578161312387475#m",
    "url": "https://nitter.net/AlArabiya_Brk/status/2036578161312387475#m",
    "title": "كندا: يجب وقف هجمات حزب الله على إسرائيل ونزع سلاحه #العربية_عاجل",
    "content": "كندا: يجب وقف هجمات حزب الله على إسرائيل ونزع سلاحه #العربية_عاجل",
    "pubDate": "Tue, 24 Mar 2026 22:57:26 GMT"
  },
  {
    "author": "alarabiya_brk",
    "id": "https://nitter.net/AlArabiya_Brk/status/2036578049794232380#m",
    "url": "https://nitter.net/AlArabiya_Brk/status/2036578049794232380#m",
    "title": "كندا: نندد بشدة بخطط إسرائيل لاحتلال أراض في جنوب لبنان #العربية_عاجل",
    "content": "كندا: نندد بشدة بخطط إسرائيل لاحتلال أراض في جنوب لبنان #العربية_عاجل",
    "pubDate": "Tue, 24 Mar 2026 22:56:59 GMT"
  },
  {
    "author": "alarabiya_brk",
    "id": "https://nitter.net/AlArabiya_Brk/status/2036576436153123268#m",
    "url": "https://nitter.net/AlArabiya_Brk/status/2036576436153123268#m",
    "title": "ترمب: أعتقد أننا سنتوصل إلى اتفاق مع إيران لكن لا أستطيع تأكيد الأمر #العربية_عاجل",
    "content": "ترمب: أعتقد أننا سنتوصل إلى اتفاق مع إيران لكن لا أستطيع تأكيد الأمر #العربية_عاجل",
    "pubDate": "Tue, 24 Mar 2026 22:50:34 GMT"
  },
  {
    "author": "alarabiya_brk",
    "id": "https://nitter.net/AlArabiya_Brk/status/2036575595014848750#m",
    "url": "https://nitter.net/AlArabiya_Brk/status/2036575595014848750#m",
    "title": "إعلام إيراني: دوي انفجارات في طهران وأصفهان #العربية_عاجل",
    "content": "إعلام إيراني: دوي انفجارات في طهران وأصفهان #العربية_عاجل",
    "pubDate": "Tue, 24 Mar 2026 22:47:14 GMT"
  },
  {
    "author": "alarabiya_brk",
    "id": "https://nitter.net/AlArabiya_Brk/status/2036574186093638144#m",
    "url": "https://nitter.net/AlArabiya_Brk/status/2036574186093638144#m",
    "title": "هيئة بحرية بريطانية: تسجيل 16 هجوما على سفن قرب إيران منذ بدء الحرب #العربية_عاجل",
    "content": "هيئة بحرية بريطانية: تسجيل 16 هجوما على سفن قرب إيران منذ بدء الحرب #العربية_عاجل",
    "pubDate": "Tue, 24 Mar 2026 22:41:38 GMT"
  },
  {
    "author": "alarabiya_brk",
    "id": "https://nitter.net/AlArabiya_Brk/status/2036573637352751134#m",
    "url": "https://nitter.net/AlArabiya_Brk/status/2036573637352751134#m",
    "title": "مراسل العربية: رصد إطلاق صواريخ إيرانية مجددا تجاه إيلات #العربية_عاجل",
    "content": "مراسل العربية: رصد إطلاق صواريخ إيرانية مجددا تجاه إيلات #العربية_عاجل",
    "pubDate": "Tue, 24 Mar 2026 22:39:27 GMT"
  },
  {
    "author": "alarabiya_brk",
    "id": "https://nitter.net/AlArabiya_Brk/status/2036571166773485891#m",
    "url": "https://nitter.net/AlArabiya_Brk/status/2036571166773485891#m",
    "title": "الدفاع البريطانية: مناطق القواعد ذات السيادة لم تكن قط جزءا من قبرص #العربية_عاجل",
    "content": "الدفاع البريطانية: مناطق القواعد ذات السيادة لم تكن قط جزءا من قبرص #العربية_عاجل",
    "pubDate": "Tue, 24 Mar 2026 22:29:38 GMT"
  },
  {
    "author": "alarabiya_brk",
    "id": "https://nitter.net/AlArabiya_Brk/status/2036571022682431777#m",
    "url": "https://nitter.net/AlArabiya_Brk/status/2036571022682431777#m",
    "title": "الدفاع البريطانية: لا خطط لدينا لتغيير مناطق القواعد في قبرص #العربية_عاجل",
    "content": "الدفاع البريطانية: لا خطط لدينا لتغيير مناطق القواعد في قبرص #العربية_عاجل",
    "pubDate": "Tue, 24 Mar 2026 22:29:04 GMT"
  },
  {
    "author": "alarabiya_brk",
    "id": "https://nitter.net/AlArabiya_Brk/status/2036570823251603754#m",
    "url": "https://nitter.net/AlArabiya_Brk/status/2036570823251603754#m",
    "title": "التلغراف: قبرص تطالب باتفاق أمني جديد بشأن القواعد البريطانية بعد هجوم إيراني #العربية_عاجل",
    "content": "التلغراف: قبرص تطالب باتفاق أمني جديد بشأن القواعد البريطانية بعد هجوم إيراني #العربية_عاجل",
    "pubDate": "Tue, 24 Mar 2026 22:28:16 GMT"
  },
  {
    "author": "alarabiya_brk",
    "id": "https://nitter.net/AlArabiya_Brk/status/2036570181091123634#m",
    "url": "https://nitter.net/AlArabiya_Brk/status/2036570181091123634#m",
    "title": "مصادر لـCNN: إيران ترى أن فانس سيكون عازما على إنهاء الصراع #العربية_عاجل",
    "content": "مصادر لـCNN: إيران ترى أن فانس سيكون عازما على إنهاء الصراع #العربية_عاجل",
    "pubDate": "Tue, 24 Mar 2026 22:25:43 GMT"
  },
  {
    "author": "alarabiya_brk",
    "id": "https://nitter.net/AlArabiya_Brk/status/2036570083586125978#m",
    "url": "https://nitter.net/AlArabiya_Brk/status/2036570083586125978#m",
    "title": "مصادر لـCNN: إيران أعربت خلال رسائل عن تفضيلها للتفاوض مع فانس #العربية_عاجل",
    "content": "مصادر لـCNN: إيران أعربت خلال رسائل عن تفضيلها للتفاوض مع فانس #العربية_عاجل",
    "pubDate": "Tue, 24 Mar 2026 22:25:20 GMT"
  },
  {
    "author": "alarabiya_brk",
    "id": "https://nitter.net/AlArabiya_Brk/status/2036567107706483037#m",
    "url": "https://nitter.net/AlArabiya_Brk/status/2036567107706483037#m",
    "title": "رويترز: انخفاض العقود الآجلة للخام الأميركي أكثر من 4% إلى 88.46 دولارا للبرميل #العربية_عاجل",
    "content": "رويترز: انخفاض العقود الآجلة للخام الأميركي أكثر من 4% إلى 88.46 دولارا للبرميل #العربية_عاجل",
    "pubDate": "Tue, 24 Mar 2026 22:13:30 GMT"
  },
  {
    "author": "alarabiya_brk",
    "id": "https://nitter.net/AlArabiya_Brk/status/2036566637747274233#m",
    "url": "https://nitter.net/AlArabiya_Brk/status/2036566637747274233#m",
    "title": "الصحة اللبنانية: 3 قتلى بغارة على بلدة حبوش جنوب لبنان #العربية_عاجل",
    "content": "الصحة اللبنانية: 3 قتلى بغارة على بلدة حبوش جنوب لبنان #العربية_عاجل",
    "pubDate": "Tue, 24 Mar 2026 22:11:38 GMT"
  },
  {
    "author": "alarabiya_brk",
    "id": "https://nitter.net/AlArabiya_Brk/status/2036563714736873927#m",
    "url": "https://nitter.net/AlArabiya_Brk/status/2036563714736873927#m",
    "title": "مراسل العربية: اعتراض صاروخ في القدس #العربية_عاجل",
    "content": "مراسل العربية: اعتراض صاروخ في القدس #العربية_عاجل",
    "pubDate": "Tue, 24 Mar 2026 22:00:01 GMT"
  },
  {
    "author": "alarabiya_brk",
    "id": "https://nitter.net/AlArabiya_Brk/status/2036563227820085497#m",
    "url": "https://nitter.net/AlArabiya_Brk/status/2036563227820085497#m",
    "title": "مراسل العربية: إطلاق صواريخ اعتراض في القدس تجاه صاروخ إيراني \n\nقناة العربية",
    "content": "مراسل العربية: إطلاق صواريخ اعتراض في القدس تجاه صاروخ إيراني \nVideo",
    "pubDate": "Tue, 24 Mar 2026 21:58:05 GMT"
  },
  {
    "author": "alarabiya_brk",
    "id": "https://nitter.net/AlArabiya_Brk/status/2036562288358949235#m",
    "url": "https://nitter.net/AlArabiya_Brk/status/2036562288358949235#m",
    "title": "مراسل العربية: إطلاق صواريخ اعتراض في القدس تجاه صاروخ إيراني #العربية_عاجل",
    "content": "مراسل العربية: إطلاق صواريخ اعتراض في القدس تجاه صاروخ إيراني #العربية_عاجل",
    "pubDate": "Tue, 24 Mar 2026 21:54:21 GMT"
  },
  {
    "author": "alarabiya_brk",
    "id": "https://nitter.net/AlArabiya_Brk/status/2036561711927329098#m",
    "url": "https://nitter.net/AlArabiya_Brk/status/2036561711927329098#m",
    "title": "صفارات إنذار في القدس #العربية_عاجل",
    "content": "صفارات إنذار في القدس #العربية_عاجل",
    "pubDate": "Tue, 24 Mar 2026 21:52:04 GMT"
  }
]